setup.py
dn_db_distributions/Binomialdistribution.py
dn_db_distributions/Gaussiandistribution.py
dn_db_distributions/Generaldistribution.py
dn_db_distributions/__init__.py
dn_db_distributions.egg-info/PKG-INFO
dn_db_distributions.egg-info/SOURCES.txt
dn_db_distributions.egg-info/dependency_links.txt
dn_db_distributions.egg-info/not-zip-safe
dn_db_distributions.egg-info/top_level.txt